cbwheeldiff2/__init__.py
cbwheeldiff2-0.0.1.dist-info/WHEEL
cbwheeldiff2-0.0.1.dist-info/METADATA
./cbwheeldiff2-0.0.1.dist-info/RECORD
cbwheeldiff2-0.0.1.dist-info/RECORD