Metadata-Version: 2.4
Name: cbwheeldiff2
Version: 0.0.1
Summary: The mysteries continue in this Python package!
Author-email: Caleb <calebbrown@google.com>
